{
    "node_url": "http://host.docker.internal:8547",
    "db_dsn": "postgres://user:postgres@db_pool:6432/db",
    "redis_url": "redis://redis",
    "kafka_url": "kafka:9092",
    "kafka_topic": "eth",
    "data_collection": [
        {
            "mode": "partial",
            "start_block": 16890447,
            "end_block": 17090847,
            "contracts": [
                {
                    "address": "0xED5AF388653567Af2F388E6224dC7C4b3241C544",
                    "symbol": "Azuki",
                    "category": "erc721",
                    "events": [
                        "TransferNonFungibleEvent"
                    ]
                },
                {
                    "address": "0xBC4CA0EdA7647A8aB7C2061c2E118A18a936f13D",
                    "symbol": "BAYC",
                    "category": "erc721",
                    "events": [
                        "TransferNonFungibleEvent"
                    ]
                },
                {
                    "address": "0xED5AF388653567Af2F388E6224dC7C4b3241C544",
                    "symbol": "AZUKI",
                    "category": "erc721",
                    "events": [
                        "TransferNonFungibleEvent"
                    ]
                },
                {
                    "address": "0x9b8b9c7C02be0bD0AA4D669bF6a1f6003424c6Dc",
                    "symbol": "ASSOC",
                    "category": "erc721",
                    "events": [
                        "TransferNonFungibleEvent"
                    ]
                },
                {
                    "address": "0xdAC17F958D2ee523a2206206994597C13D831ec7",
                    "symbol": "USDT",
                    "category": "erc20",
                    "events": [
                        "TransferFungibleEvent",
                        "MintFungibleEvent",
                        "BurnFungibleEvent"
                    ]
                },
                {
                    "address": "0xc00e94Cb662C3520282E6f5717214004A7f26888",
                    "symbol": "Compound",
                    "category": "erc20",
                    "events": [
                        "TransferFungibleEvent",
                        "MintFungibleEvent",
                        "BurnFungibleEvent"
                    ]
                },
                {
                    "address": "0x7fc66500c84a76ad7e9c93437bfc5ac33e2ddae9",
                    "symbol": "Aave",
                    "category": "erc20",
                    "events": [
                        "TransferFungibleEvent",
                        "MintFungibleEvent",
                        "BurnFungibleEvent"
                    ]
                },
                {
                    "address": "0xD533a949740bb3306d119CC777fa900bA034cd52",
                    "symbol": "Curve",
                    "category": "erc20",
                    "events": [
                        "TransferFungibleEvent",
                        "MintFungibleEvent",
                        "BurnFungibleEvent"
                    ]
                },
                {
                    "address": "0x92d6c1e31e14520e676a687f0a93788b716beff5",
                    "symbol": "Dydx",
                    "category": "erc20",
                    "events": [
                        "TransferFungibleEvent",
                        "MintFungibleEvent",
                        "BurnFungibleEvent"
                    ]
                },
                {
                    "address": "0x5C69bEe701ef814a2B6a3EDD4B1652CB9cc5aA6f",
                    "symbol": "UniSwap V2 Factory",
                    "category": "UniSwapV2Factory",
                    "events": []
                },
                {
                    "address": "0xe6c78983b07a07e0523b57e18aa23d3ae2519e05",
                    "symbol": "UniSwap V2 Pair UETH-ULCK",
                    "category": "UniSwapV2Pair",
                    "events": [
                        "MintPairEvent",
                        "BurnPairEvent",
                        "SwapPairEvent"
                    ]
                },
                {
                    "address": "0x21b8065d10f73ee2e260e5b47d3344d3ced7596e",
                    "symbol": "UniSwap V2 Pair WISE-WETH",
                    "category": "UniSwapV2Pair",
                    "events": [
                        "MintPairEvent",
                        "BurnPairEvent",
                        "SwapPairEvent"
                    ]
                },
                {
                    "address": "0xb4e16d0168e52d35cacd2c6185b44281ec28c9dc",
                    "symbol": "UniSwap V2 Pair USDC-WETH",
                    "category": "UniSwapV2Pair",
                    "events": [
                        "MintPairEvent",
                        "BurnPairEvent",
                        "SwapPairEvent"
                    ]
                },
                {
                    "address": "0x0d4a11d5eeaac28ec3f61d100daf4d40471f1852",
                    "symbol": "UniSwap V2 Pair WETH-USDT",
                    "category": "UniSwapV2Pair",
                    "events": [
                        "MintPairEvent",
                        "BurnPairEvent",
                        "SwapPairEvent"
                    ]
                },
                {
                    "address": "0x7d7e813082ef6c143277c71786e5be626ec77b20",
                    "symbol": "UniSwap V2 Pair DELTA-WETH",
                    "category": "UniSwapV2Pair",
                    "events": [
                        "MintPairEvent",
                        "BurnPairEvent",
                        "SwapPairEvent"
                    ]
                },
                {
                    "address": "0x61b62c5d56ccd158a38367ef2f539668a06356ab",
                    "symbol": "UniSwap V2 Pair FNK-USDT",
                    "category": "UniSwapV2Pair",
                    "events": [
                        "MintPairEvent",
                        "BurnPairEvent",
                        "SwapPairEvent"
                    ]
                },
                {
                    "address": "0x0617d5ffb29c03ac35f1863b8a50ce1b52d446f6",
                    "symbol": "UniSwap V2 Pair RK:ETH-ROOT",
                    "category": "UniSwapV2Pair",
                    "events": [
                        "MintPairEvent",
                        "BurnPairEvent",
                        "SwapPairEvent"
                    ]
                },
                {
                    "address": "0x3041cbd36888becc7bbcbc0045e3b1f144466f5f",
                    "symbol": "UniSwap V2 Pair USDC-USDT",
                    "category": "UniSwapV2Pair",
                    "events": [
                        "MintPairEvent",
                        "BurnPairEvent",
                        "SwapPairEvent"
                    ]
                },
                {
                    "address": "0xae461ca67b15dc8dc81ce7615e0320da1a9ab8d5",
                    "symbol": "UniSwap V2 Pair DAI-USDC",
                    "category": "UniSwapV2Pair",
                    "events": [
                        "MintPairEvent",
                        "BurnPairEvent",
                        "SwapPairEvent"
                    ]
                },
                {
                    "address": "0xe2f95dae6c5763c357447fe1ffb3f2a884bdc0b5",
                    "symbol": "UniSwap V2 Pair ETH2POS-DC",
                    "category": "UniSwapV2Pair",
                    "events": [
                        "MintPairEvent",
                        "BurnPairEvent",
                        "SwapPairEvent"
                    ]
                },
                {
                    "address": "0x9816f26f43c4c02df0daae1a0ba6a4dcd30b8ab7",
                    "symbol": "UniSwap V2 Pair M2-wPE",
                    "category": "UniSwapV2Pair",
                    "events": [
                        "MintPairEvent",
                        "BurnPairEvent",
                        "SwapPairEvent"
                    ]
                },
                {
                    "address": "0xa478c2975ab1ea89e8196811f51a7b7ade33eb11",
                    "symbol": "UniSwap V2 Pair DAI-WETH",
                    "category": "UniSwapV2Pair",
                    "events": [
                        "MintPairEvent",
                        "BurnPairEvent",
                        "SwapPairEvent"
                    ]
                },
                {
                    "address": "0x93512394a82d278b9961e3891a59c6dc1c2e4f98",
                    "symbol": "UniSwap V2 Pair HANU-GOJ",
                    "category": "UniSwapV2Pair",
                    "events": [
                        "MintPairEvent",
                        "BurnPairEvent",
                        "SwapPairEvent"
                    ]
                },
                {
                    "address": "0xc86881ef494b049fe3e624ae6fdf542f58ab1931",
                    "symbol": "UniSwap V2 Pair DBL-BLUE",
                    "category": "UniSwapV2Pair",
                    "events": [
                        "MintPairEvent",
                        "BurnPairEvent",
                        "SwapPairEvent"
                    ]
                },
                {
                    "address": "0x48918f57fa7210ea7b20f23da8420e68df3578fe",
                    "symbol": "UniSwap V2 Pair HANU-MIA",
                    "category": "UniSwapV2Pair",
                    "events": [
                        "MintPairEvent",
                        "BurnPairEvent",
                        "SwapPairEvent"
                    ]
                },
                {
                    "address": "0xe1573b9d29e2183b1af0e743dc2754979a40d237",
                    "symbol": "UniSwap V2 Pair FXS-FRAX",
                    "category": "UniSwapV2Pair",
                    "events": [
                        "MintPairEvent",
                        "BurnPairEvent",
                        "SwapPairEvent"
                    ]
                },
                {
                    "address": "0x0af81cd5d9c124b4859d65697a4cd10ee223746a",
                    "symbol": "UniSwap V2 Pair XXi-WETH",
                    "category": "UniSwapV2Pair",
                    "events": [
                        "MintPairEvent",
                        "BurnPairEvent",
                        "SwapPairEvent"
                    ]
                },
                {
                    "address": "0x9ec96dcb54331626b79d8450a3daa9bcfa02e0b0",
                    "symbol": "UniSwap V2 Pair BHNY-wPE",
                    "category": "UniSwapV2Pair",
                    "events": [
                        "MintPairEvent",
                        "BurnPairEvent",
                        "SwapPairEvent"
                    ]
                },
                {
                    "address": "0xccb63225a7b19dcf66717e4d40c9a72b39331d61",
                    "symbol": "UniSwap V2 Pair MC-WETH",
                    "category": "UniSwapV2Pair",
                    "events": [
                        "MintPairEvent",
                        "BurnPairEvent",
                        "SwapPairEvent"
                    ]
                },
                {
                    "address": "0x48d20b3e529fb3dd7d91293f80638df582ab2daa",
                    "symbol": "UniSwap V2 Pair WETH-CAW",
                    "category": "UniSwapV2Pair",
                    "events": [
                        "MintPairEvent",
                        "BurnPairEvent",
                        "SwapPairEvent"
                    ]
                },
                {
                    "address": "0x7b73644935b8e68019ac6356c40661e1bc315860",
                    "symbol": "UniSwap V2 Pair ELON-WETH",
                    "category": "UniSwapV2Pair",
                    "events": [
                        "MintPairEvent",
                        "BurnPairEvent",
                        "SwapPairEvent"
                    ]
                },
                {
                    "address": "0xd3d2e2692501a5c9ca623199d38826e513033a17",
                    "symbol": "UniSwap V2 Pair UNI-WETH",
                    "category": "UniSwapV2Pair",
                    "events": [
                        "MintPairEvent",
                        "BurnPairEvent",
                        "SwapPairEvent"
                    ]
                },
                {
                    "address": "0x97be09f2523b39b835da9ea3857cfa1d3c660cbb",
                    "symbol": "UniSwap V2 Pair vUSD-VOW",
                    "category": "UniSwapV2Pair",
                    "events": [
                        "MintPairEvent",
                        "BurnPairEvent",
                        "SwapPairEvent"
                    ]
                },
                {
                    "address": "0xbb2b8038a1640196fbe3e38816f3e67cba72d940",
                    "symbol": "UniSwap V2 Pair WBTC-WETH",
                    "category": "UniSwapV2Pair",
                    "events": [
                        "MintPairEvent",
                        "BurnPairEvent",
                        "SwapPairEvent"
                    ]
                },
                {
                    "address": "0x9928e4046d7c6513326ccea028cd3e7a91c7590a",
                    "symbol": "UniSwap V2 Pair FEI-TRIBE",
                    "category": "UniSwapV2Pair",
                    "events": [
                        "MintPairEvent",
                        "BurnPairEvent",
                        "SwapPairEvent"
                    ]
                },
                {
                    "address": "0xa43fe16908251ee70ef74718545e4fe6c5ccec9f",
                    "symbol": "UniSwap V2 Pair PEPE-WETH",
                    "category": "UniSwapV2Pair",
                    "events": [
                        "MintPairEvent",
                        "BurnPairEvent",
                        "SwapPairEvent"
                    ]
                },
                {
                    "address": "0x149148acc3b06b8cc73af3a10e84189243a35925",
                    "symbol": "UniSwap V2 Pair BigSB-USDC",
                    "category": "UniSwapV2Pair",
                    "events": [
                        "MintPairEvent",
                        "BurnPairEvent",
                        "SwapPairEvent"
                    ]
                },
                {
                    "address": "0x9c4fe5ffd9a9fc5678cfbd93aa2d4fd684b67c4c",
                    "symbol": "UniSwap V2 Pair PAXG-WETH",
                    "category": "UniSwapV2Pair",
                    "events": [
                        "MintPairEvent",
                        "BurnPairEvent",
                        "SwapPairEvent"
                    ]
                },
                {
                    "address": "0xeb7b5294c79b0369315ed7fe76b52d3108b0a62d",
                    "symbol": "UniSwap V2 Pair USDC-JAY",
                    "category": "UniSwapV2Pair",
                    "events": [
                        "MintPairEvent",
                        "BurnPairEvent",
                        "SwapPairEvent"
                    ]
                },
                {
                    "address": "0x0ee0cb563a52ae1170ac34fbb94c50e89adde4bd",
                    "symbol": "UniSwap V2 Pair WAXE-WETH",
                    "category": "UniSwapV2Pair",
                    "events": [
                        "MintPairEvent",
                        "BurnPairEvent",
                        "SwapPairEvent"
                    ]
                },
                {
                    "address": "0x25647e01bd0967c1b9599fa3521939871d1d0888",
                    "symbol": "UniSwap V2 Pair WETH-SUPER",
                    "category": "UniSwapV2Pair",
                    "events": [
                        "MintPairEvent",
                        "BurnPairEvent",
                        "SwapPairEvent"
                    ]
                },
                {
                    "address": "0xf778c77ec3696879cb5ac814984655aefe66d716",
                    "symbol": "UniSwap V2 Pair UETH-DAPE",
                    "category": "UniSwapV2Pair",
                    "events": [
                        "MintPairEvent",
                        "BurnPairEvent",
                        "SwapPairEvent"
                    ]
                },
                {
                    "address": "0x873056a02255872514f05249d93228d788fe4fb4",
                    "symbol": "UniSwap V2 Pair DG-USDC",
                    "category": "UniSwapV2Pair",
                    "events": [
                        "MintPairEvent",
                        "BurnPairEvent",
                        "SwapPairEvent"
                    ]
                },
                {
                    "address": "0x0179d00549b44d3161b9c260815f8a5947a541b3",
                    "symbol": "UniSwap V2 Pair ULS-UETH",
                    "category": "UniSwapV2Pair",
                    "events": [
                        "MintPairEvent",
                        "BurnPairEvent",
                        "SwapPairEvent"
                    ]
                },
                {
                    "address": "0xca7c2771d248dcbe09eabe0ce57a62e18da178c0",
                    "symbol": "UniSwap V2 Pair WETH-FLOKI",
                    "category": "UniSwapV2Pair",
                    "events": [
                        "MintPairEvent",
                        "BurnPairEvent",
                        "SwapPairEvent"
                    ]
                },
                {
                    "address": "0x2d0ba902badaa82592f0e1c04c71d66cea21d921",
                    "symbol": "UniSwap V2 Pair WETH-BTT",
                    "category": "UniSwapV2Pair",
                    "events": [
                        "MintPairEvent",
                        "BurnPairEvent",
                        "SwapPairEvent"
                    ]
                },
                {
                    "address": "0x8c1c499b1796d7f3c2521ac37186b52de024e58c",
                    "symbol": "UniSwap V2 Pair RAD-USDC",
                    "category": "UniSwapV2Pair",
                    "events": [
                        "MintPairEvent",
                        "BurnPairEvent",
                        "SwapPairEvent"
                    ]
                },
                {
                    "address": "0x6ada49aeccf6e556bb7a35ef0119cc8ca795294a",
                    "symbol": "UniSwap V2 Pair WOO-WETH",
                    "category": "UniSwapV2Pair",
                    "events": [
                        "MintPairEvent",
                        "BurnPairEvent",
                        "SwapPairEvent"
                    ]
                },
                {
                    "address": "0x684b00a5773679f88598a19976fbeb25a68e9a5f",
                    "symbol": "UniSwap V2 Pair eXRD-USDC",
                    "category": "UniSwapV2Pair",
                    "events": [
                        "MintPairEvent",
                        "BurnPairEvent",
                        "SwapPairEvent"
                    ]
                },
                {
                    "address": "0x97e1fcb93ae7267dbafad23f7b9afaa08264cfd8",
                    "symbol": "UniSwap V2 Pair UFO-WETH",
                    "category": "UniSwapV2Pair",
                    "events": [
                        "MintPairEvent",
                        "BurnPairEvent",
                        "SwapPairEvent"
                    ]
                },
                {
                    "address": "0x470e8de2ebaef52014a47cb5e6af86884947f08c",
                    "symbol": "UniSwap V2 Pair WETH-FOX",
                    "category": "UniSwapV2Pair",
                    "events": [
                        "MintPairEvent",
                        "BurnPairEvent",
                        "SwapPairEvent"
                    ]
                },
                {
                    "address": "0x6d74443bb2d50785989a7212ebfd3a8dbabd1f60",
                    "symbol": "UniSwap V2 Pair PAXG-USDC",
                    "category": "UniSwapV2Pair",
                    "events": [
                        "MintPairEvent",
                        "BurnPairEvent",
                        "SwapPairEvent"
                    ]
                },
                {
                    "address": "0x4028daac072e492d34a3afdbef0ba7e35d8b55c4",
                    "symbol": "UniSwap V2 Pair stETH-WETH",
                    "category": "UniSwapV2Pair",
                    "events": [
                        "MintPairEvent",
                        "BurnPairEvent",
                        "SwapPairEvent"
                    ]
                },
                {
                    "address": "0xa29fe6ef9592b5d408cca961d0fb9b1faf497d6d",
                    "symbol": "UniSwap V2 Pair WETH-DEXT",
                    "category": "UniSwapV2Pair",
                    "events": [
                        "MintPairEvent",
                        "BurnPairEvent",
                        "SwapPairEvent"
                    ]
                },
                {
                    "address": "0xe3d3551bb608e7665472180a20280630d9e938aa",
                    "symbol": "UniSwap V2 Pair WETH-SAITAMA",
                    "category": "UniSwapV2Pair",
                    "events": [
                        "MintPairEvent",
                        "BurnPairEvent",
                        "SwapPairEvent"
                    ]
                },
                {
                    "address": "0x570febdf89c07f256c75686caca215289bb11cfc",
                    "symbol": "UniSwap V2 Pair ERN-WETH",
                    "category": "UniSwapV2Pair",
                    "events": [
                        "MintPairEvent",
                        "BurnPairEvent",
                        "SwapPairEvent"
                    ]
                },
                {
                    "address": "0x44a7b882b550f3af2e1fbe644316cbd07e90a145",
                    "symbol": "UniSwap V2 Pair scUSD-USDC",
                    "category": "UniSwapV2Pair",
                    "events": [
                        "MintPairEvent",
                        "BurnPairEvent",
                        "SwapPairEvent"
                    ]
                },
                {
                    "address": "0x11181bd3baf5ce2a478e98361985d42625de35d1",
                    "symbol": "UniSwap V2 Pair ASTO-USDC",
                    "category": "UniSwapV2Pair",
                    "events": [
                        "MintPairEvent",
                        "BurnPairEvent",
                        "SwapPairEvent"
                    ]
                },
                {
                    "address": "0x4a08cf0a7bca217c24b9ee99c0395052f3707d68",
                    "symbol": "UniSwap V2 Pair VOLT-WETH",
                    "category": "UniSwapV2Pair",
                    "events": [
                        "MintPairEvent",
                        "BurnPairEvent",
                        "SwapPairEvent"
                    ]
                },
                {
                    "address": "0x3016a43b482d0480460f6625115bd372fe90c6bf",
                    "symbol": "UniSwap V2 Pair ShibDoge-WETH",
                    "category": "UniSwapV2Pair",
                    "events": [
                        "MintPairEvent",
                        "BurnPairEvent",
                        "SwapPairEvent"
                    ]
                },
                {
                    "address": "0x5281e311734869c64ca60ef047fd87759397efe6",
                    "symbol": "UniSwap V2 Pair WETH-CULT",
                    "category": "UniSwapV2Pair",
                    "events": [
                        "MintPairEvent",
                        "BurnPairEvent",
                        "SwapPairEvent"
                    ]
                },
                {
                    "address": "0xf6c4e4f339912541d3f8ed99dba64a1372af5e5b",
                    "symbol": "UniSwap V2 Pair USDT-HEZ",
                    "category": "UniSwapV2Pair",
                    "events": [
                        "MintPairEvent",
                        "BurnPairEvent",
                        "SwapPairEvent"
                    ]
                },
                {
                    "address": "0xec54859519293b8784bc5bf28144166f313618af",
                    "symbol": "UniSwap V2 Pair DAI-O",
                    "category": "UniSwapV2Pair",
                    "events": [
                        "MintPairEvent",
                        "BurnPairEvent",
                        "SwapPairEvent"
                    ]
                },
                {
                    "address": "0x23707ccaa36590803397578b4c44d6d0ae16c5b6",
                    "symbol": "UniSwap V2 Pair USDC-scUSD",
                    "category": "UniSwapV2Pair",
                    "events": [
                        "MintPairEvent",
                        "BurnPairEvent",
                        "SwapPairEvent"
                    ]
                },
                {
                    "address": "0x343fd171caf4f0287ae6b87d75a8964dc44516ab",
                    "symbol": "UniSwap V2 Pair PNK-WETH",
                    "category": "UniSwapV2Pair",
                    "events": [
                        "MintPairEvent",
                        "BurnPairEvent",
                        "SwapPairEvent"
                    ]
                },
                {
                    "address": "0x3ab2ebbe52f4a80098a461cf9ecdade2ed645fc4",
                    "symbol": "UniSwap V2 Pair ETHx-WETH",
                    "category": "UniSwapV2Pair",
                    "events": [
                        "MintPairEvent",
                        "BurnPairEvent",
                        "SwapPairEvent"
                    ]
                },
                {
                    "address": "0x2af039cccff4e491237a99ed51a009138c8aba9f",
                    "symbol": "UniSwap V2 Pair WETH-SFTX",
                    "category": "UniSwapV2Pair",
                    "events": [
                        "MintPairEvent",
                        "BurnPairEvent",
                        "SwapPairEvent"
                    ]
                },
                {
                    "address": "0xc5be99a02c6857f9eac67bbce58df5572498f40c",
                    "symbol": "UniSwap V2 Pair WETH-AMPL",
                    "category": "UniSwapV2Pair",
                    "events": [
                        "MintPairEvent",
                        "BurnPairEvent",
                        "SwapPairEvent"
                    ]
                },
                {
                    "address": "0xf8d99cf7046dedcb1dc8cfc309aa96946c9b9db2",
                    "symbol": "UniSwap V2 Pair XFIT-USDT",
                    "category": "UniSwapV2Pair",
                    "events": [
                        "MintPairEvent",
                        "BurnPairEvent",
                        "SwapPairEvent"
                    ]
                },
                {
                    "address": "0x8ef79d6c328c25da633559c20c75f638a4863462",
                    "symbol": "UniSwap V2 Pair QOM-WETH",
                    "category": "UniSwapV2Pair",
                    "events": [
                        "MintPairEvent",
                        "BurnPairEvent",
                        "SwapPairEvent"
                    ]
                },
                {
                    "address": "0xe532b04d2f2e921dfec69e132e9214d2f82df304",
                    "symbol": "UniSwap V2 Pair FLUT-DAI",
                    "category": "UniSwapV2Pair",
                    "events": [
                        "MintPairEvent",
                        "BurnPairEvent",
                        "SwapPairEvent"
                    ]
                },
                {
                    "address": "0x6033368e4a402605294c91cf5c03d72bd96e7d8d",
                    "symbol": "UniSwap V2 Pair X2Y2-WETH",
                    "category": "UniSwapV2Pair",
                    "events": [
                        "MintPairEvent",
                        "BurnPairEvent",
                        "SwapPairEvent"
                    ]
                },
                {
                    "address": "0xa5e9c917b4b821e4e0a5bbefce078ab6540d6b5e",
                    "symbol": "UniSwap V2 Pair STARL-WETH",
                    "category": "UniSwapV2Pair",
                    "events": [
                        "MintPairEvent",
                        "BurnPairEvent",
                        "SwapPairEvent"
                    ]
                },
                {
                    "address": "0x603fb61742baed14c6b5922cef1ac0a2320c4cb6",
                    "symbol": "UniSwap V2 Pair UETH-ROOT",
                    "category": "UniSwapV2Pair",
                    "events": [
                        "MintPairEvent",
                        "BurnPairEvent",
                        "SwapPairEvent"
                    ]
                },
                {
                    "address": "0x2caccf71bdf8fff97c06a46eca29b611b1a74b5e",
                    "symbol": "UniSwap V2 Pair SWFL-WETH",
                    "category": "UniSwapV2Pair",
                    "events": [
                        "MintPairEvent",
                        "BurnPairEvent",
                        "SwapPairEvent"
                    ]
                },
                {
                    "address": "0xc730ef0f4973da9cc0ab8ab291890d3e77f58f79",
                    "symbol": "UniSwap V2 Pair AUDIO-WETH",
                    "category": "UniSwapV2Pair",
                    "events": [
                        "MintPairEvent",
                        "BurnPairEvent",
                        "SwapPairEvent"
                    ]
                },
                {
                    "address": "0xcaa004418eb42cdf00cb057b7c9e28f0ffd840a5",
                    "symbol": "UniSwap V2 Pair WILD-WETH",
                    "category": "UniSwapV2Pair",
                    "events": [
                        "MintPairEvent",
                        "BurnPairEvent",
                        "SwapPairEvent"
                    ]
                },
                {
                    "address": "0x7924a818013f39cf800f5589ff1f1f0def54f31f",
                    "symbol": "UniSwap V2 Pair LON-WETH",
                    "category": "UniSwapV2Pair",
                    "events": [
                        "MintPairEvent",
                        "BurnPairEvent",
                        "SwapPairEvent"
                    ]
                },
                {
                    "address": "0xaf996125e98b5804c00ffdb4f7ff386307c99a00",
                    "symbol": "UniSwap V2 Pair XFI-WETH",
                    "category": "UniSwapV2Pair",
                    "events": [
                        "MintPairEvent",
                        "BurnPairEvent",
                        "SwapPairEvent"
                    ]
                },
                {
                    "address": "0x2f0b1417aa42ebf0b4ca1154212847f6094d708d",
                    "symbol": "UniSwap V2 Pair GF-WETH",
                    "category": "UniSwapV2Pair",
                    "events": [
                        "MintPairEvent",
                        "BurnPairEvent",
                        "SwapPairEvent"
                    ]
                },
                {
                    "address": "0xfcd13ea0b906f2f87229650b8d93a51b2e839ebd",
                    "symbol": "UniSwap V2 Pair DOGE-USDT",
                    "category": "UniSwapV2Pair",
                    "events": [
                        "MintPairEvent",
                        "BurnPairEvent",
                        "SwapPairEvent"
                    ]
                },
                {
                    "address": "0x9ff68f61ca5eb0c6606dc517a9d44001e564bb66",
                    "symbol": "UniSwap V2 Pair BOTTO-WETH",
                    "category": "UniSwapV2Pair",
                    "events": [
                        "MintPairEvent",
                        "BurnPairEvent",
                        "SwapPairEvent"
                    ]
                },
                {
                    "address": "0xffa98a091331df4600f87c9164cd27e8a5cd2405",
                    "symbol": "UniSwap V2 Pair POLS-WETH",
                    "category": "UniSwapV2Pair",
                    "events": [
                        "MintPairEvent",
                        "BurnPairEvent",
                        "SwapPairEvent"
                    ]
                },
                {
                    "address": "0xc3d7aa944105d3fafe07fc1822102449c916a8d0",
                    "symbol": "UniSwap V2 Pair WDOGE-WETH",
                    "category": "UniSwapV2Pair",
                    "events": [
                        "MintPairEvent",
                        "BurnPairEvent",
                        "SwapPairEvent"
                    ]
                },
                {
                    "address": "0x336ef4e633b1117dca08c1a57f4139c62c32c935",
                    "symbol": "UniSwap V2 Pair BEND-WETH",
                    "category": "UniSwapV2Pair",
                    "events": [
                        "MintPairEvent",
                        "BurnPairEvent",
                        "SwapPairEvent"
                    ]
                },
                {
                    "address": "0xc0067d751fb1172dbab1fa003efe214ee8f419b6",
                    "symbol": "UniSwap V2 Pair DOGE-WETH",
                    "category": "UniSwapV2Pair",
                    "events": [
                        "MintPairEvent",
                        "BurnPairEvent",
                        "SwapPairEvent"
                    ]
                },
                {
                    "address": "0xdd8f50f1059c50d7d75fe2f5d7d262964fb2ae98",
                    "symbol": "UniSwap V2 Pair KDOE-WETH",
                    "category": "UniSwapV2Pair",
                    "events": [
                        "MintPairEvent",
                        "BurnPairEvent",
                        "SwapPairEvent"
                    ]
                },
                {
                    "address": "0x9def9511fec79f83afcbffe4776b1d817dc775ae",
                    "symbol": "UniSwap V2 Pair ANT-WETH",
                    "category": "UniSwapV2Pair",
                    "events": [
                        "MintPairEvent",
                        "BurnPairEvent",
                        "SwapPairEvent"
                    ]
                },
                {
                    "address": "0x9af0f334f9f451ce9e650278e56fec212f35cec1",
                    "symbol": "UniSwap V2 Pair KOO-WETH",
                    "category": "UniSwapV2Pair",
                    "events": [
                        "MintPairEvent",
                        "BurnPairEvent",
                        "SwapPairEvent"
                    ]
                },
                {
                    "address": "0xb079d6be3faf5771e354586dbc47d0a3d37c34fb",
                    "symbol": "UniSwap V2 Pair DFI-WETH",
                    "category": "UniSwapV2Pair",
                    "events": [
                        "MintPairEvent",
                        "BurnPairEvent",
                        "SwapPairEvent"
                    ]
                },
                {
                    "address": "0xaf21b0ec0197e63a5c6cc30c8e947eb8165c6212",
                    "symbol": "UniSwap V2 Pair WETH-DETS",
                    "category": "UniSwapV2Pair",
                    "events": [
                        "MintPairEvent",
                        "BurnPairEvent",
                        "SwapPairEvent"
                    ]
                },
                {
                    "address": "0x9c84f58bb51fabd18698efe95f5bab4f33e96e8f",
                    "symbol": "UniSwap V2 Pair LFT-WETH",
                    "category": "UniSwapV2Pair",
                    "events": [
                        "MintPairEvent",
                        "BurnPairEvent",
                        "SwapPairEvent"
                    ]
                },
                {
                    "address": "0x70ec2fa6eccf4010eaf572d1c1a7bcbc72dec983",
                    "symbol": "UniSwap V2 Pair WETH-ROOK",
                    "category": "UniSwapV2Pair",
                    "events": [
                        "MintPairEvent",
                        "BurnPairEvent",
                        "SwapPairEvent"
                    ]
                },
                {
                    "address": "0xcd6bcca48069f8588780dfa274960f15685aee0e",
                    "symbol": "UniSwap V2 Pair \u2697\ufe0f-WETH",
                    "category": "UniSwapV2Pair",
                    "events": [
                        "MintPairEvent",
                        "BurnPairEvent",
                        "SwapPairEvent"
                    ]
                },
                {
                    "address": "0x29f07e631a2f990e1f6117c6285a44e746b1f090",
                    "symbol": "UniSwap V2 Pair EVN-WETH",
                    "category": "UniSwapV2Pair",
                    "events": [
                        "MintPairEvent",
                        "BurnPairEvent",
                        "SwapPairEvent"
                    ]
                },
                {
                    "address": "0x48200057593487b93311b03c845afda306a90e2a",
                    "symbol": "UniSwap V2 Pair KAP-WETH",
                    "category": "UniSwapV2Pair",
                    "events": [
                        "MintPairEvent",
                        "BurnPairEvent",
                        "SwapPairEvent"
                    ]
                },
                {
                    "address": "0xa2107fa5b38d9bbd2c461d6edf11b11a50f6b974",
                    "symbol": "UniSwap V2 Pair LINK-WETH",
                    "category": "UniSwapV2Pair",
                    "events": [
                        "MintPairEvent",
                        "BurnPairEvent",
                        "SwapPairEvent"
                    ]
                },
                {
                    "address": "0xc6a45ecdc8bcef94c476647be1303fd83d438cd0",
                    "symbol": "UniSwap V2 Pair SNAIL-WETH",
                    "category": "UniSwapV2Pair",
                    "events": [
                        "MintPairEvent",
                        "BurnPairEvent",
                        "SwapPairEvent"
                    ]
                },
                {
                    "address": "0x67cea36eeb36ace126a3ca6e21405258130cf33c",
                    "symbol": "UniSwap V2 Pair USDC-TSUKA",
                    "category": "UniSwapV2Pair",
                    "events": [
                        "MintPairEvent",
                        "BurnPairEvent",
                        "SwapPairEvent"
                    ]
                },
                {
                    "address": "0x6a164da2cdae5f1836c8fe6d683c3df4a0a65e5c",
                    "symbol": "UniSwap V2 Pair DJ15-WETH",
                    "category": "UniSwapV2Pair",
                    "events": [
                        "MintPairEvent",
                        "BurnPairEvent",
                        "SwapPairEvent"
                    ]
                },
                {
                    "address": "0xe471f93c2be15b64e9ec63bbf485446cb934e8c4",
                    "symbol": "UniSwap V2 Pair imgnAI-WETH",
                    "category": "UniSwapV2Pair",
                    "events": [
                        "MintPairEvent",
                        "BurnPairEvent",
                        "SwapPairEvent"
                    ]
                },
                {
                    "address": "0xf3b675df63fb4889180d290a338fc15c0766fd64",
                    "symbol": "UniSwap V2 Pair SPOOL-DAI",
                    "category": "UniSwapV2Pair",
                    "events": [
                        "MintPairEvent",
                        "BurnPairEvent",
                        "SwapPairEvent"
                    ]
                },
                {
                    "address": "0x035a397725d3c9fc5ddd3e56066b7b64c749014e",
                    "symbol": "UniSwap V2 Pair HEX-HDRN",
                    "category": "UniSwapV2Pair",
                    "events": [
                        "MintPairEvent",
                        "BurnPairEvent",
                        "SwapPairEvent"
                    ]
                },
                {
                    "address": "0xf82d8ec196fb0d56c6b82a8b1870f09502a49f88",
                    "symbol": "UniSwap V2 Pair KISHU-WETH",
                    "category": "UniSwapV2Pair",
                    "events": [
                        "MintPairEvent",
                        "BurnPairEvent",
                        "SwapPairEvent"
                    ]
                },
                {
                    "address": "0x582e3da39948c6339433008703211ad2c13eb2ac",
                    "symbol": "UniSwap V2 Pair WETH-USD",
                    "category": "UniSwapV2Pair",
                    "events": [
                        "MintPairEvent",
                        "BurnPairEvent",
                        "SwapPairEvent"
                    ]
                },
                {
                    "address": "0xf1603432a96cb371f03d77501d1d7f55070cf8cc",
                    "symbol": "UniSwap V2 Pair SHARE-USD",
                    "category": "UniSwapV2Pair",
                    "events": [
                        "MintPairEvent",
                        "BurnPairEvent",
                        "SwapPairEvent"
                    ]
                },
                {
                    "address": "0x0f23d49bc92ec52ff591d091b3e16c937034496e",
                    "symbol": "UniSwap V2 Pair WOJAK-WETH",
                    "category": "UniSwapV2Pair",
                    "events": [
                        "MintPairEvent",
                        "BurnPairEvent",
                        "SwapPairEvent"
                    ]
                },
                {
                    "address": "0xaf31fd9c3b0350424bf96e551d2d1264d8466205",
                    "symbol": "UniSwap V2 Pair WETH-PUSH",
                    "category": "UniSwapV2Pair",
                    "events": [
                        "MintPairEvent",
                        "BurnPairEvent",
                        "SwapPairEvent"
                    ]
                },
                {
                    "address": "0xdf60e6416fcf8c955fddf01148753a911f7a5905",
                    "symbol": "UniSwap V2 Pair KUMA-WETH",
                    "category": "UniSwapV2Pair",
                    "events": [
                        "MintPairEvent",
                        "BurnPairEvent",
                        "SwapPairEvent"
                    ]
                },
                {
                    "address": "0x09bc52b9eb7387ede639fc10ce5fa01cbcbf2b17",
                    "symbol": "UniSwap V2 Pair ECO-USDC",
                    "category": "UniSwapV2Pair",
                    "events": [
                        "MintPairEvent",
                        "BurnPairEvent",
                        "SwapPairEvent"
                    ]
                }
            ]
        }
    ]
}
